jupyter_utility_widgets/__init__.py
jupyter_utility_widgets/file_explorer.py
jupyter_utility_widgets/filter_design.py
jupyter_utility_widgets/audio/__init__.py
jupyter_utility_widgets/audio/audio.js
jupyter_utility_widgets/chat/audio_message.py
jupyter_utility_widgets/chat/chat_display.py
jupyter_utility_widgets/chat/chat_interface.py
jupyter_utility_widgets/chat/content_input.py
jupyter_utility_widgets/chat/content_input_protocol.py
jupyter_utility_widgets/chat/message.py
jupyter_utility_widgets/chat/message_display.py
jupyter_utility_widgets/chat/message_wrapper.js
jupyter_utility_widgets/chat/text_message.js
jupyter_utility_widgets/chat/text_message.py
jupyter_utility_widgets/input/__init__.py
jupyter_utility_widgets/input/numerical.py
jupyter_utility_widgets/plot/__init__.py
jupyter_utility_widgets/plot/filter.py
jupyter_utility_widgets/plot/specgram_examiner.py
jupyter_utility_widgets/plot/figures/__init__.py
jupyter_utility_widgets/plot/figures/base.py
jupyter_utility_widgets/plot/figures/indicators.py
jupyter_utility_widgets/plot/figures/lines.py
jupyter_utility_widgets/plot/figures/specgram.py
jupyter_utility_widgets/selector/__init__.py
jupyter_utility_widgets/selector/index_selector.py
jupyter_utility_widgets/utility/numpy_parameter_converter.py
jupyter_utility_widgets-0.0.7.dist-info/licenses/LICENSE
jupyter_utility_widgets-0.0.7.dist-info/METADATA
jupyter_utility_widgets-0.0.7.dist-info/WHEEL
jupyter_utility_widgets-0.0.7.dist-info/top_level.txt
jupyter_utility_widgets-0.0.7.dist-info/RECORD
