Metadata-Version: 2.4
Name: jupyter-utility-widgets
Version: 0.0.7
Summary: Assortment of reusable common jupyter widget patterns
Project-URL: Homepage, https://github.com/shaielc/jupyter-utility-widgets
Project-URL: Source, https://github.com/shaielc/jupyter-utility-widgets
Project-URL: Bug Tracker, https://github.com/shaielc/jupyter-utility-widgets/issues
License-File: LICENSE
Requires-Dist: ipywidgets>=8.0.2
Requires-Dist: numpydoc
Requires-Dist: numpy
Requires-Dist: scipy
Requires-Dist: matplotlib
Requires-Dist: ipympl
Dynamic: license-file
